{
  "result": {
    "item": "galacticraftcore:engine",
    "data": 1
  },
  "pattern": [
    "ZYZ",
    "ZWZ",
    "XVX"
  ],
  "type": "minecraft:crafting_shaped",
  "key": {
    "V": {
      "item": "galacticraftcore:air_vent"
    },
    "W": {
      "item": "galacticraftcore:fuel_canister_partial",
      "data": 1
    },
    "X": {
      "item": "galacticraftcore:heavy_plating"
    },
    "Y": {
      "item": "minecraft:wool",
      "data": 4
    },
    "Z": {
      "item": "galacticraftcore:item_basic_moon",
      "data": 1
    }
  }
}